sciogovterminal/__init__.py
sciogovterminal/sciogovterminal.py
sciogovterminal-0.1.1.dist-info/LICENSE
sciogovterminal-0.1.1.dist-info/METADATA
sciogovterminal-0.1.1.dist-info/WHEEL
sciogovterminal-0.1.1.dist-info/entry_points.txt
sciogovterminal-0.1.1.dist-info/top_level.txt
sciogovterminal-0.1.1.dist-info/zip-safe
sciogovterminal-0.1.1.dist-info/RECORD
