Metadata-Version: 2.1
Name: sciogovterminal
Version: 0.1.1
Summary: Sciogovterminal: Browse "The State Council Information Office of the People's Republic of China" in the terminal.
Home-page: https://github.com/CharlesPikachu/sciogovterminal
Author: Zhenchao Jin
Author-email: charlesblwx@gmail.com
License: Apache License 2.0
Platform: UNKNOWN
Classifier: License :: OSI Approved :: Apache Software License
Classifier: Programming Language :: Python :: 3
Classifier: Intended Audience :: Developers
Classifier: Operating System :: OS Independent
License-File: LICENSE
Requires-Dist: requests
Requires-Dist: beautifulsoup4
Requires-Dist: pynput
Requires-Dist: click
